docs/GaN_findTDE_example.ipynb
docs/Installation.rst
docs/Makefile
docs/Tutorials.rst
docs/conf.py
docs/dev_todo.md
docs/findtde.defect_analysis.rst
docs/findtde.io.rst
docs/findtde.multi_tde.rst
docs/findtde.plotting.rst
docs/findtde.rst
docs/findtde.tde_analysis.rst
docs/findtde.utils.rst
docs/findtde.vasp_vel_write.rst
docs/ftde_logo.png
docs/ftde_logo_dark.png
docs/index.rst
docs/make.bat
docs/requirements.txt
examples/GaN_findTDE_example.ipynb
examples/AlN_VASP/AlN_TDE_example.md
examples/GaN_LAMMPS/GaN_LAMMPS_TDE_example.md
examples/GaN_LAMMPS/all_tde_data_lmp.csv
examples/GaN_LAMMPS/gan_lmp_errs_run_info_ALL.txt
examples/GaN_LAMMPS/gan_lmp_pseudo_keys_ALL.csv
examples/GaN_LAMMPS/latt_dirs_to_calc.csv
examples/GaN_LAMMPS/sph_directions_ext_set1.csv
examples/GaN_LAMMPS/sph_directions_ext_set2.csv
examples/GaN_LAMMPS/sph_directions_ext_set3.csv
examples/GaN_LAMMPS/tde_lineplot.png
examples/GaN_LAMMPS/176S_ga34_lmp/176S_ga34_data.csv
examples/GaN_LAMMPS/176S_ga34_lmp/176S_ga34_out.txt
examples/GaN_LAMMPS/176S_ga34_lmp/KE_calcs_list.txt
examples/GaN_LAMMPS/176S_ga34_lmp/10eV/AlGaN.sw
examples/GaN_LAMMPS/176S_ga34_lmp/10eV/POSCAR
examples/GaN_LAMMPS/176S_ga34_lmp/10eV/dump.final
examples/GaN_LAMMPS/176S_ga34_lmp/10eV/input.tde
examples/GaN_LAMMPS/176S_ga34_lmp/10eV/log.lammps
examples/GaN_LAMMPS/176S_ga34_lmp/10eV/read_data.lmp
examples/GaN_LAMMPS/176S_ga34_lmp/10eV/slurm-6231657.out
examples/GaN_LAMMPS/176S_ga34_lmp/18eV/AlGaN.sw
examples/GaN_LAMMPS/176S_ga34_lmp/18eV/POSCAR
examples/GaN_LAMMPS/176S_ga34_lmp/18eV/dump.final
examples/GaN_LAMMPS/176S_ga34_lmp/18eV/input.tde
examples/GaN_LAMMPS/176S_ga34_lmp/18eV/log.lammps
examples/GaN_LAMMPS/176S_ga34_lmp/18eV/read_data.lmp
examples/GaN_LAMMPS/176S_ga34_lmp/18eV/slurm-6231924.out
examples/GaN_LAMMPS/176S_ga34_lmp/26eV/AlGaN.sw
examples/GaN_LAMMPS/176S_ga34_lmp/26eV/POSCAR
examples/GaN_LAMMPS/176S_ga34_lmp/26eV/dump.final
examples/GaN_LAMMPS/176S_ga34_lmp/26eV/input.tde
findtde-1.4.0.dist-info/licenses/LICENSE
findtde-1.4.0.dist-info/METADATA
findtde-1.4.0.dist-info/WHEEL
findtde-1.4.0.dist-info/entry_points.txt
findtde-1.4.0.dist-info/top_level.txt
findtde-1.4.0.dist-info/RECORD
