Metadata-Version: 2.4
Name: findtde
Version: 1.4.0
Summary: Set of scripts to facilitate easy calculations of threshold displacement energies for materials in VASP/LAMMPS using ab initio/classical molecular dynamics.
Author-email: Alexander Hauck <ash5615@psu.edu>
License: MIT License
Project-URL: Homepage, https://findTDE.readthedocs.io/en/latest/
Project-URL: Repository, https://github.com/hauck-as/findTDE
Classifier: Programming Language :: Python :: 3
Classifier: License :: OSI Approved :: MIT License
Classifier: Operating System :: OS Independent
Requires-Python: >=3.6
License-File: LICENSE
Requires-Dist: requests
Requires-Dist: importlib-metadata; python_version < "3.12"
Requires-Dist: numpy>=1.24.4
Requires-Dist: pandas==2.1.4
Requires-Dist: matplotlib
Requires-Dist: plotly
Requires-Dist: pymatgen
Requires-Dist: ase>=3.23.0
Requires-Dist: fortranformat
Requires-Dist: nbformat
Requires-Dist: kaleido
Dynamic: license-file
